tricorder/__init__.py
tricorder/bioinf/__init__.py
tricorder/eval/__init__.py
tricorder/eval/segmentation/EvaluateSegmentationWrapper.py
tricorder/eval/segmentation/__init__.py
tricorder/math/__init__.py
tricorder/math/transforms/__init__.py
tricorder/math/transforms/fourier.py
tricorder/math/transforms/fourier_helpers.py
tricorder/mri/__init__.py
tricorder/mri/data/__init__.py
tricorder/mri/data/dicom.py
tricorder/mri/data/nifti.py
tricorder/mri/data/sitk.py
tricorder/mri/transforms.py
tricorder/pykit/__init__.py
tricorder/torch/__init__.py
tricorder/torch/modules/__init__.py
tricorder/torch/modules/padding.py
tricorder/torch/transforms.py
tricorder-0.1.0.dist-info/LICENSE
tricorder-0.1.0.dist-info/METADATA
tricorder-0.1.0.dist-info/WHEEL
tricorder-0.1.0.dist-info/RECORD
